<?xml version="1.0" encoding="UTF-8"?>
<beans xmlns="http://www.springframework.org/schema/beans"
    xmlns:xsi="http://www.w3.org/2001/XMLSchema-instance"
    xmlns:util="http://www.springframework.org/schema/util"
    xmlns:context="http://www.springframework.org/schema/context"
    xmlns:aop="http://www.springframework.org/schema/aop"
    xsi:schemaLocation="
    http://www.springframework.org/schema/beans http://www.springframework.org/schema/beans/spring-beans.xsd
    http://www.springframework.org/schema/util http://www.springframework.org/schema/util/spring-util.xsd
    http://www.springframework.org/schema/aop http://www.springframework.org/schema/aop/spring-aop-2.5.xsd
    http://www.springframework.org/schema/context http://www.springframework.org/schema/context/spring-context-3.1.xsd">

    <aop:config>
      <aop:aspect id="kakaduMetadataTransformAspect" ref="kakaduResultFinishingTransformer">
    	<aop:pointcut id="kakaduTransformPointcut"
    		      expression="bean(kakaduMetadataTransformer)"
    		      />
    	<aop:after-returning pointcut-ref="kakaduTransformPointcut"
    			     returning="metadataList"
    			     method="transform"/>
      </aop:aspect>
    </aop:config>

    <bean id="kakaduResultFinishingTransformer" class="cz.nkp.differ.compare.metadata.external.ResultFinishingTransformer">
      <property name="mapOfEntryNames">
	<map>
	</map>
      </property>
      
      <property name="entryTransformers">
	<map>
	</map>
      </property>
      
      <property name="entryReplacers">
    	<map>
	  <entry key="Size" value-ref="sizeInBracketsReplacer"/>
    	</map>
      </property>
    </bean>
    
    <bean id="kakaduMetadataTransformer" class="cz.nkp.differ.compare.metadata.external.RegexpTransformer">
      <property name="mapOfRegexp">
    	<map>
    	  <entry key="Color depth"   value="Sprecision=[\ \t]*(.*)"/>
	  <entry key="Size" value="Ssize=[\ \t]*(.*)"/>
	  <entry key="Components" value="Scomponents=[\ \t]*(.*)"/>
	  <entry key="Origin" value="Sorigin=[\ \t]*(.*)"/>
	  <entry key="Tile origin" value="Stile_origin=[\ \t]*(.*)"/>
	  <entry key="Tiles" value="Stiles=[\ \t]*(.*)"/>
    	  <entry key="Sampling"   value="Ssampling=[\ \t]*(.*)"/>
    	  <entry key="Dimensions"   value="Sdims=[\ \t]*(.*)"/>
    	  <entry key="Dimensions"   value="Dimensions=[\ \t]*(.*)"/>
    	  <entry key="Transformation"   value="Cycc=[\ \t]*(.*)"/>
    	  <entry key="CMCT"   value="Ccmct=[\ \t]*(.*)"/>
    	  <entry key="Number of quality layers"   value="Clayers=[\ \t]*(.*)"/>
    	  <entry key="Start of packet header"   value="Cuse_sop=[\ \t]*(.*)"/>
    	  <entry key="End of packet header"   value="Cuse_eph=[\ \t]*(.*)"/>
    	  <entry key="Progression order"   value="Corder=[\ \t]*(.*)"/>
    	  <entry key="Number of decomposition levels"   value="Clevels=[\ \t]*([0-9]*)"/>
	  <entry key="ADS" value="Cads=[\ \t]*(.*)"/>
	  <entry key="Decomp" value="Cdecomp=[\ \t]*(.*)"/>
	  <entry key="Compression" value="Creversible=[\ \t]*(.*)"/>
	  <entry key="Type of algorithm" value="Ckernels=[\ \t]*(.*)"/>
	  <entry key="ATK" value="Catk=[\ \t]*(.*)"/>
	  <entry key="Precints" value="Cuse_precincts=[\ \t]*(.*)"/>
	  <entry key="Code block size" value="Cblk=[\ \t]*(.*)"/>
	  <entry key="Bypass" value="Cmodes=[\ \t]*(.*)"/>
	  <entry key="Derived" value="Cabs_steps=[\ \t]*(.*)"/>
	  <entry key="Consumed" value="Consumed[\ \t]+(.*)"/>
    	</map>
      </property>
      <property name="listOfRegexp">
    	<list>
	  <value>([^=]+)=(.+)</value>
    	</list>
      </property>
    </bean>
    
    <bean id="kakaduMetadataExtractor" class="cz.nkp.differ.compare.metadata.external.ExternalMetadataExtractor">
      <property name="source" value="kakadu"/>
      <property name="transformer" ref="kakaduMetadataTransformer"/>
      <property name="programArguments">
    	<list>
    	  <value>${kakadu.binary}</value>
	  <value>-i</value>
    	  <value>{file}</value>
	  <value>-record</value>
	  <value>/dev/stdout</value>
	  <value>-no_decode</value>
    	</list>
      </property>
      <property name="units" ref="units"/>
      <property name="supportedFileExtensions">
	<list>
	  <value>jp2000</value>
	  <value>jp2</value>
	  <value>jpf</value>
	  <value>jpp</value>
	</list>
      </property>
    </bean>
</beans>
