<?xml version="1.0" encoding="UTF-8"?>
<beans xmlns="http://www.springframework.org/schema/beans"
       xmlns:xsi="http://www.w3.org/2001/XMLSchema-instance"
       xmlns:util="http://www.springframework.org/schema/util"
       xmlns:context="http://www.springframework.org/schema/context"
       xsi:schemaLocation="http://www.springframework.org/schema/beans http://www.springframework.org/schema/beans/spring-beans.xsd
			   http://www.springframework.org/schema/util http://www.springframework.org/schema/util/spring-util.xsd
			   http://www.springframework.org/schema/context http://www.springframework.org/schema/context/spring-context-3.1.xsd">
  
  <util:set id="identificationProperties">
    <value>MIME type</value>
    <value>Type of format</value>
    <value>Version of format</value>
    <value>Version</value>
  </util:set>
  
  <util:set id="validationProperties">
    <value>Validation (well formed and valid)</value>
    <value>Signature box length is valid</value>
    <value>Signature is valid</value>
    <value>Box length is valid</value>
    <value>Brand is valid</value>
    <value>Minor version is valid</value>
    <value>Compatibility list is valid</value>
    <value>Image header box length is valid</value>
    <value>Image header box height is valid</value>
    <value>Image header box width is valid</value>
    <value>nC is valid</value>
    <value>bPC is valid</value>
    <value>C is valid</value>
    <value>unkC is valid</value>
    <value>iPR is valid</value>
    <value>Meth is valid</value>
    <value>Prec is valid</value>
    <value>Approximation is valid</value>
    <value>Enum CS is valid</value>
    <value>Capture resolution box length is valid</value>
    <value>vRcN is valid</value>
    <value>vRcD is valid</value>
    <value>hRcN is valid</value>
    <value>hRcD is valid</value>
    <value>vRcE is valid</value>
    <value>hRcE is valid</value>
    <value>Contains capture or display resolution box</value>
    <value>No more than one capture resolution box</value>
    <value>No more than one display resolution box</value>
    <value>Contains image header box</value>
    <value>Contains colour specification box</value>
    <value>First jp2 header box is image header box</value>
    <value>No more than one image header box</value>
    <value>No more than one bits pre component box</value>
    <value>No more than one palette box</value>
    <value>No more than one component mapping box</value>
    <value>No more than one channel definition box</value>
    <value>No more than one resolution box</value>
    <value>Colour specification boxes are contiguous</value>
    <value>Palette and component mapping boxes only together</value>
    <value>Box length is valid</value>
    <value>Codestream start with SOC marker</value>
    <value>Found SIZ marker</value>
    <value>l size is valid</value>
    <value>r size is valid</value>
    <value>x size is valid</value>
    <value>y size is valid</value>
    <value>xO size is valid</value>
    <value>yO size is valid</value>
    <value>xT size is valid</value>
    <value>yT size is valid</value>
    <value>xTO size is valid</value>
    <value>yTO size is valid</value>
    <value>c size is valid</value>
    <value>l size consistency with c size</value>
    <value>s size is valid</value>
    <value>xR size is valid</value>
    <value>yR size is valid</value>
    <value>s size is valid</value>
    <value>l cod is valid</value>
    <value>cod order is valid</value>
    <value>Cod layers is valid</value>
    <value>Multiple component transformation is valid</value>
    <value>Cod levels is valid</value>
    <value>l cod consistent with levels precincts</value>
    <value>Code block with exponent is valid</value>
    <value>Code block height exponent is valid</value>
    <value>Sum height width exponent is valid</value>
    <value>Cod transformation is valid</value>
    <value>l qcd is valid</value>
    <value>q style is valid</value>
    <value>Found COD marker</value>
    <value>Found QCD marker</value>
    <value>Quantization consistent with levels</value>
    <value>Found expected number of tiles</value>
    <value>Found expected number of tile parts</value>
    <value>l sot is valid</value>
    <value>i sot is valid</value>
    <value>p sot is valid</value>
    <value>tp sot is valid</value>
    <value>Found SOD marker</value>
    <value>Fount next tile part or EOC</value>
    <value>Found EOC marker</value>
    <value>Contains signature box</value>
    <value>Contains file type box</value>
    <value>Contains JP2 header box</value>
    <value>Contains contiguous codestream box</value>
    <value>First box is signature box</value>
    <value>Second box is file type box</value>
    <value>Location JP2 header box is valid</value>
    <value>No more than one signature box</value>
    <value>No more than one file type box</value>
    <value>No more tna one JP2 header box</value>
    <value>Heigt consistent with SIZ</value>
    <value>Width consistent with SIZ</value>
    <value>NC consistent with SIZ</value>
    <value>bPC sign consistent with SIZ</value>
    <value>bPC depth consistent with SIZ</value>
  </util:set>
  
  <util:set id="characterizationProperties">
    <value>Pixels per second</value>
    <value>Gamma</value>
    <value>Depth of blue channel</value>
    <value>Depth of green channel</value>
    <value>Depth of red channel</value>
    <value>Copyright</value>
    <value>Compression quality</value>
    <value>File name</value>
    <value>File path</value>
    <value>Color depth</value>
    <value>Color space</value>
    <value>Color type</value>
    <value>Universal unique identifier (UUID)</value>
    <value>File size</value>
    <value>Image height</value>
    <value>Image width</value>
    <value>File created</value>
    <value>File last modified</value>
    <value>Compression</value>
    <value>Resolution horizontal</value>
    <value>Resolution vertical</value>
    <value>Number of channels</value>
    <value>Number of pixels</value>
    <value>ICC profile</value>
    <value>Samples per pixel</value>
    <value>Orientation</value>
    <value>Interlace</value>
    <value>Media black point</value>
    <value>Media white point</value>
    <value>Overall kurtosis</value>
    <value>Overall max</value>
    <value>Overall mean</value>
    <value>Overall max</value>
    <value>Overall min</value>
    <value>Overall standard deviation</value>
    <value>Luminance</value>
    <value>Software</value>
    <value>Resolution unit</value>
    <value>Thumbnail</value>
    <value>Measurement backing</value>
    <value>Measurement geometry</value>
    <value>Measurement flare</value>
    <value>Measurement illuminant</value>
    <value>Measurement observer</value>
    <value>Media black point</value>
    <value>Media white point</value>
    <value>Page geometry</value>
    <value>Transparent color</value>
    <value>Units</value>
    <value>Pixel units</value>
    <value>Pixels per unit x</value>
    <value>Pixels per unit y</value>
    <value>Profile file signature</value>
    <value>Sampling</value>
    <value>Dimension</value>
    <value>Transformation</value>
    <value>CMCT</value>
    <value>Number of quality layers</value>
    <value>Start of packet header</value>
    <value>End of packet header</value>
    <value>Progression order</value>
    <value>Number of decomposition levels</value>
    <value>ADS</value>
    <value>Decomp</value>
    <value>Type of algorithm</value>
    <value>ATK</value>
    <value>Precincts</value>
    <value>Code block size</value>
    <value>Bypass</value>
    <value>Derived</value>
  </util:set>

</beans>
